{
  "Data": [
    {
      "comp_id": "TC4",
      "emp_id": "TC4002",
      "lname": "Lname42",
      "fname": "Fname42",
      "suffix": "",
      "mname": "L",
      "division": "DIVISION 1",
      "department": "DEPARTMENT 2",
      "monthly_pay": 55000,
      "basic_salary": 12719.82,
      "holiday_pay": 2308.88,
      "premium_ot": 5466.94,
      "otherben_before_tax": 12,
      "total_taxable": 75507.64,
      "adj_after_tax": 110,
      "otherben_after_tax": 2072,
      "deminimis": 20,
      "total_nontaxable": 2202,
      "employee_sss": 481,
      "employee_philhealth": 206.5,
      "employee_hdmf": 51,
      "total_employee_stat": 738.5,
      "employer_sss": 862,
      "employer_philhealth": 192.5,
      "employer_hdmf": 40,
      "total_employer_stat": 1094.5,
      "total_tax_withheld": 330,
      "total_net": 22379.64
    },
    {
      "comp_id": "TC4",
      "emp_id": "TC4007",
      "lname": "Lname47",
      "fname": "Fname47",
      "suffix": "",
      "mname": "",
      "division": "DIVISION 1",
      "department": "DEPARTMENT 1",
      "monthly_pay": 272988.17,
      "basic_salary": 103578.78,
      "holiday_pay": 0,
      "premium_ot": 0,
      "otherben_before_tax": 0,
      "total_taxable": 376566.95,
      "adj_after_tax": 0,
      "otherben_after_tax": 0,
      "deminimis": 0,
      "total_nontaxable": 0,
      "employee_sss": 5512.5,
      "employee_philhealth": 1729.04,
      "employee_hdmf": 1076,
      "total_employee_stat": 8317.54,
      "employer_sss": 11077.5,
      "employer_philhealth": 1729.04,
      "employer_hdmf": 1076,
      "total_employer_stat": 13882.54,
      "total_tax_withheld": 0,
      "total_net": 103578.78
    },
    {
      "comp_id": "TC4",
      "emp_id": "TC4009",
      "lname": "Lname49",
      "fname": "Fname49",
      "suffix": "",
      "mname": "W",
      "division": "DIVISION 1",
      "department": "DEPARTMENT 1",
      "monthly_pay": 40000,
      "basic_salary": 19250,
      "holiday_pay": 0,
      "premium_ot": 0,
      "otherben_before_tax": 0,
      "total_taxable": 59250,
      "adj_after_tax": 0,
      "otherben_after_tax": 0,
      "deminimis": 0,
      "total_nontaxable": 0,
      "employee_sss": 400,
      "employee_philhealth": 300,
      "employee_hdmf": 50,
      "total_employee_stat": 750,
      "employer_sss": 815,
      "employer_philhealth": 300,
      "employer_hdmf": 50,
      "total_employer_stat": 1165,
      "total_tax_withheld": 0,
      "total_net": 19250
    },
    {
      "comp_id": "TC4",
      "emp_id": "TC4003",
      "lname": "Test",
      "fname": "Test",
      "suffix": "",
      "mname": "",
      "division": "DIVISION 1",
      "department": "DEPARTMENT 1",
      "monthly_pay": 36679.75,
      "basic_salary": 17798.48,
      "holiday_pay": 1145.04,
      "premium_ot": 0,
      "otherben_before_tax": 0,
      "total_taxable": 55623.27,
      "adj_after_tax": 0,
      "otherben_after_tax": 0,
      "deminimis": 0,
      "total_nontaxable": 0,
      "employee_sss": 0,
      "employee_philhealth": 0,
      "employee_hdmf": 0,
      "total_employee_stat": 0,
      "employer_sss": 0,
      "employer_philhealth": 0,
      "employer_hdmf": 0,
      "total_employer_stat": 0,
      "total_tax_withheld": 100,
      "total_net": 18843.52
    },
    {
      "comp_id": "TC4",
      "emp_id": "TC4004",
      "lname": "TestL1",
      "fname": "Test1",
      "suffix": "",
      "mname": "TEST111",
      "division": "DIVISION 1",
      "department": "DEPARTMENT 1",
      "monthly_pay": 6364333.34,
      "basic_salary": 2924400,
      "holiday_pay": 800,
      "premium_ot": 2000,
      "otherben_before_tax": 4000,
      "total_taxable": 9295533.34,
      "adj_after_tax": 5001,
      "otherben_after_tax": 200,
      "deminimis": 500,
      "total_nontaxable": 5701,
      "employee_sss": 1600,
      "employee_philhealth": 1800,
      "employee_hdmf": 100,
      "total_employee_stat": 3500,
      "employer_sss": 3260,
      "employer_philhealth": 1800,
      "employer_hdmf": 100,
      "total_employer_stat": 5160,
      "total_tax_withheld": -300,
      "total_net": 2937201
    },
    {
      "comp_id": "TC4",
      "emp_id": "TC4005",
      "lname": "TestL2",
      "fname": "Test2",
      "suffix": "",
      "mname": "TEST112",
      "division": "DIVISION 1",
      "department": "DEPARTMENT 1",
      "monthly_pay": 26083.33,
      "basic_salary": 4663.71,
      "holiday_pay": 0,
      "premium_ot": 0,
      "otherben_before_tax": 0,
      "total_taxable": 30747.04,
      "adj_after_tax": 0,
      "otherben_after_tax": 0,
      "deminimis": 0,
      "total_nontaxable": 0,
      "employee_sss": 225,
      "employee_philhealth": 91.29,
      "employee_hdmf": 20,
      "total_employee_stat": 336.29,
      "employer_sss": 431,
      "employer_philhealth": 91.29,
      "employer_hdmf": 20,
      "total_employer_stat": 542.29,
      "total_tax_withheld": 0,
      "total_net": 4663.71
    }
  ]
}